norch/__init__.py
norch/libtensor.so
norch/tensor.py
norch/autograd/__init__.py
norch/autograd/functions.py
norch/csrc/cpu.cpp
norch/csrc/cpu.h
norch/csrc/cuda.cu
norch/csrc/cuda.h
norch/csrc/distributed.cpp
norch/csrc/distributed.h
norch/csrc/tensor.cpp
norch/csrc/tensor.h
norch/distributed/__init__.py
norch/distributed/distributed.py
norch/nn/__init__.py
norch/nn/activation.py
norch/nn/functional.py
norch/nn/loss.py
norch/nn/module.py
norch/nn/parallel.py
norch/nn/parameter.py
norch/nn/modules/__init__.py
norch/nn/modules/linear.py
norch/norchvision/__init__.py
norch/norchvision/transforms.py
norch/norchvision/datasets/__init__.py
norch/norchvision/datasets/mnist.py
norch/optim/__init__.py
norch/optim/optimizer.py
norch/optim/optimizers/__init__.py
norch/optim/optimizers/sgd.py
norch/utils/__init__.py
norch/utils/functions.py
norch/utils/utils_unittests.py
norch/utils/data/__init__.py
norch/utils/data/batch.py
norch/utils/data/dataloader.py
norch/utils/data/dataset.py
norch/utils/data/distributed.py
norch/utils/data/example.py
tests/__init__.py
tests/test_autograd.py
tests/test_dataset.py
tests/test_distributed.py
tests/test_nn.py
tests/test_operations.py
norch-0.0.7.dist-info/METADATA
norch-0.0.7.dist-info/WHEEL
norch-0.0.7.dist-info/top_level.txt
norch-0.0.7.dist-info/RECORD
